ConMorph.cp312-win_amd64.pyd
CondtionalMorphology.cp312-win_amd64.pyd
ConMorph-1.2.0.dist-info/METADATA
ConMorph-1.2.0.dist-info/WHEEL
ConMorph-1.2.0.dist-info/top_level.txt
ConMorph-1.2.0.dist-info/RECORD
