Metadata-Version: 2.2
Name: ConMorph
Version: 1.2.0
Summary: Python package for conditional morphology
Dynamic: summary
